odoo/addons/account_refund_payment_term/README.rst
odoo/addons/account_refund_payment_term/__init__.py
odoo/addons/account_refund_payment_term/__manifest__.py
odoo/addons/account_refund_payment_term/i18n/account_refund_payment_term.pot
odoo/addons/account_refund_payment_term/i18n/es.po
odoo/addons/account_refund_payment_term/i18n/fr.po
odoo/addons/account_refund_payment_term/i18n/it.po
odoo/addons/account_refund_payment_term/models/__init__.py
odoo/addons/account_refund_payment_term/models/account_move.py
odoo/addons/account_refund_payment_term/models/partner.py
odoo/addons/account_refund_payment_term/readme/CONTRIBUTORS.rst
odoo/addons/account_refund_payment_term/readme/DESCRIPTION.rst
odoo/addons/account_refund_payment_term/readme/ROADMAP.rst
odoo/addons/account_refund_payment_term/readme/USAGE.rst
odoo/addons/account_refund_payment_term/static/description/icon.png
odoo/addons/account_refund_payment_term/static/description/index.html
odoo/addons/account_refund_payment_term/tests/__init__.py
odoo/addons/account_refund_payment_term/tests/test_refund_payment_term.py
odoo/addons/account_refund_payment_term/views/res_partner_view.xml
odoo14_addon_account_refund_payment_term-14.0.1.0.1.dev8.dist-info/METADATA
odoo14_addon_account_refund_payment_term-14.0.1.0.1.dev8.dist-info/WHEEL
odoo14_addon_account_refund_payment_term-14.0.1.0.1.dev8.dist-info/top_level.txt
odoo14_addon_account_refund_payment_term-14.0.1.0.1.dev8.dist-info/RECORD
